sigmaepsilon/deepdict/__init__.py
sigmaepsilon/deepdict/deepdict.py
sigmaepsilon/deepdict/exceptions.py
sigmaepsilon/deepdict/utils.py
sigmaepsilon_deepdict-3.0.1.dist-info/LICENSE
sigmaepsilon_deepdict-3.0.1.dist-info/METADATA
sigmaepsilon_deepdict-3.0.1.dist-info/WHEEL
sigmaepsilon_deepdict-3.0.1.dist-info/RECORD
