Metadata-Version: 2.1
Name: sigmaepsilon.deepdict
Version: 3.0.1
Summary: Common developer utilities for Python projects.
Home-page: https://github.com/sigma-epsilon/sigmaepsilon.deepdict
License: MIT
Keywords: data structures,dictionary,Python,tree
Author: Bence Balogh
Author-email: bencebalogh@sigmaepsilon.com
Maintainer: Bence Balogh
Maintainer-email: bencebalogh@sigmaepsilon.com
Requires-Python: >=3.10,<4.0
Classifier: Development Status :: 5 - Production/Stable
Classifier: License :: OSI Approved :: MIT License
Classifier: Operating System :: OS Independent
Classifier: Programming Language :: Python :: 3
Classifier: Programming Language :: Python :: 3.10
Classifier: Programming Language :: Python :: 3.11
Classifier: Programming Language :: Python :: 3.12
Classifier: Programming Language :: Python :: 3.13
Classifier: Programming Language :: Python :: 3 :: Only
Requires-Dist: sigmaepsilon-core (>=1.2.1,<2.0.0)
Project-URL: Documentation, https://sigmaepsilondeepdict.readthedocs.io/en/latest/?badge=latest
Project-URL: Repository, https://github.com/sigma-epsilon/sigmaepsilon.deepdict
